uwTOPSIS/__init__.py
uwTOPSIS/uwTOPSIS.py
uwTOPSIS-1.0.0.dist-info/METADATA
uwTOPSIS-1.0.0.dist-info/WHEEL
uwTOPSIS-1.0.0.dist-info/top_level.txt
uwTOPSIS-1.0.0.dist-info/RECORD
