Metadata-Version: 2.1
Name: uwTOPSIS
Version: 1.0.0
Summary: Unweighted TOPSIS method
Home-page: https://github.com/Aaron-AALG/uwTOPSIS
Author: Aaron Lopez-Garcia
Author-email: alopgar3@upv.es
License: MIT
Download-URL: https://github.com/Aaron-AALG/uwTOPSIS/releases/tag/uwTOPSIS
Platform: UNKNOWN
Classifier: Programming Language :: Python :: 3.8
Classifier: License :: OSI Approved :: MIT License
Requires-Dist: numpy >=1.26.2
Requires-Dist: scipy >=1.11.4
